{
  "entity": {
    "kind": "port",
    "slug": "san-diego-ca-united-states",
    "name": "San Diego, CA, United States",
    "country": "United States",
    "region": "California"
  },
  "fetchedAt": "2026-05-21T23:33:46.021Z",
  "facts": [
    {
      "claim": "San Diego is a city on the Pacific coast of Southern California, adjacent to the Mexico–United States border.",
      "source": "wikipedia",
      "sourceUrl": "https://en.wikipedia.org/wiki/San_Diego",
      "confidence": 0.72
    },
    {
      "claim": "It is known for its mild Mediterranean climate, extensive beaches and parks, long association with the United States Navy, and recent emergence as a wireless, electronics, healthcare, and biotechnology development center.",
      "source": "wikipedia",
      "sourceUrl": "https://en.wikipedia.org/wiki/San_Diego",
      "confidence": 0.72
    }
  ],
  "errors": [],
  "sourcesUsed": [
    "wikipedia"
  ]
}
