{
  "entity": {
    "kind": "port",
    "slug": "roatan-honduras",
    "name": "Roatan, Honduras",
    "country": "Honduras",
    "region": "Caribbean"
  },
  "fetchedAt": "2026-05-21T23:32:56.680Z",
  "facts": [
    {
      "claim": "Roatán is an island in the Caribbean, about 65 kilometres (40 mi) off the northern coast of Honduras.",
      "source": "wikipedia",
      "sourceUrl": "https://en.wikipedia.org/wiki/Roat%C3%A1n",
      "confidence": 0.72
    },
    {
      "claim": "The largest of the Bay Islands of Honduras, it is located between the islands of Utila and Guanaja.",
      "source": "wikipedia",
      "sourceUrl": "https://en.wikipedia.org/wiki/Roat%C3%A1n",
      "confidence": 0.72
    }
  ],
  "errors": [],
  "sourcesUsed": [
    "wikipedia"
  ]
}
