{
  "entity": {
    "kind": "ship",
    "slug": "celebrity-eclipse",
    "name": "Celebrity Eclipse",
    "cruiseLine": "Celebrity Cruises"
  },
  "fetchedAt": "2026-05-21T22:42:07.116Z",
  "facts": [
    {
      "claim": "Discover Celebrity Eclipse. View the award-winning luxury cruise ship's deck plan, staterooms, dining options, things to do and upcoming sailings.",
      "source": "official-cruise-line",
      "sourceUrl": "https://www.celebritycruises.com/cruise-ships/celebrity-eclipse",
      "confidence": 0.85
    },
    {
      "claim": "Celebrity Eclipse is a Solstice-class cruise ship operated by Celebrity Cruises, a subsidiary of Royal Caribbean Group.",
      "source": "wikipedia",
      "sourceUrl": "https://en.wikipedia.org/wiki/Celebrity_Eclipse",
      "confidence": 0.72
    },
    {
      "claim": "The 122,000 GT-vessel followed sister ships Celebrity Solstice and Celebrity Equinox as the third Solstice-class ship in the fleet.",
      "source": "wikipedia",
      "sourceUrl": "https://en.wikipedia.org/wiki/Celebrity_Eclipse",
      "confidence": 0.72
    }
  ],
  "errors": [],
  "sourcesUsed": [
    "wikipedia",
    "official-cruise-line"
  ]
}
