{
  "entity": {
    "kind": "ship",
    "slug": "aurora",
    "name": "Aurora",
    "cruiseLine": "P&O Cruises"
  },
  "fetchedAt": "2026-05-21T23:19:00.929Z",
  "facts": [
    {
      "claim": "An aurora is a natural light display in Earth's upper atmosphere caused by charged particles from the Sun colliding with atoms in the atmosphere.",
      "source": "wikipedia",
      "sourceUrl": "https://en.wikipedia.org/wiki/Aurora",
      "confidence": 0.72
    },
    {
      "claim": "When observed in high-latitude regions they are called polar lights and aurora polaris.",
      "source": "wikipedia",
      "sourceUrl": "https://en.wikipedia.org/wiki/Aurora",
      "confidence": 0.72
    },
    {
      "claim": "In the Arctic they are called the northern lights or aurora borealis; in the Antarctic, the term southern lights or aurora australis is used.",
      "source": "wikipedia",
      "sourceUrl": "https://en.wikipedia.org/wiki/Aurora",
      "confidence": 0.72
    },
    {
      "claim": "Auroras display dynamic patterns of radiant light that appear as curtains, rays, spirals or dynamic flickers covering the entire sky.",
      "source": "wikipedia",
      "sourceUrl": "https://en.wikipedia.org/wiki/Aurora",
      "confidence": 0.72
    }
  ],
  "errors": [],
  "sourcesUsed": [
    "wikipedia"
  ]
}
